devclikit/__init__.py
devclikit/cli_factory.py
devclikit/completion.py
devclikit/exceptions.py
devclikit/loader.py
devclikit/runner.py
devclikit/utils.py
devclikit/examples/README.md
devclikit/examples/hello_world/__main__.py
devclikit/examples/hello_world/commands/hello/command.py
devclikit/examples/hello_world/commands/hello/script.py
devclikit/templates/README.md.jinja
devclikit/templates/__main__.py.jinja
devclikit/templates/command.py.jinja
devclikit/templates/script.py.jinja
devclikit-0.1.12.dist-info/METADATA
devclikit-0.1.12.dist-info/WHEEL
devclikit-0.1.12.dist-info/RECORD
