Metadata-Version: 2.4
Name: devclikit
Version: 0.1.12
Summary: Framework for building development CLIs with PEP 723 script support
Requires-Python: >=3.13
Requires-Dist: click>=8.1.7
